WETWRSM/__init__.py
WETWRSM-0.1.dist-info/LICENSE.txt
WETWRSM-0.1.dist-info/METADATA
WETWRSM-0.1.dist-info/WHEEL
WETWRSM-0.1.dist-info/top_level.txt
WETWRSM-0.1.dist-info/RECORD
